<PAMDataset>
  <PAMRasterBand band="1">
    <Description>Layer_1</Description>
    <Metadata domain="IMAGE_STRUCTURE">
      <MDI key="COMPRESSION">RLE</MDI>
    </Metadata>
    <Metadata>
      <MDI key="LAYER_TYPE">thematic</MDI>
      <MDI key="STATISTICS_EXCLUDEDVALUES"></MDI>
      <MDI key="STATISTICS_HISTOBINVALUES">0|0|508629|1392337|3269641|966992|3183555|7553862|10325614|2553150|77075097|10442046|26126504|1637314|852691|999823|10|1333|114916|708820|1764451|9137690|10223|78148|0|358223|0|0|0|0|0|0|0|0|0|0|0|0|0|0|0|0|0|0|0|0|0|0|0|0|0|0|0|0|0|0|0|0|0|0|0|0|0|0|0|0|0|0|0|0|0|0|0|0|0|0|0|0|0|0|0|0|0|0|0|0|0|0|0|0|0|0|0|0|0|0|0|0|0|0|0|0|0|0|0|0|0|0|0|0|0|0|0|0|0|0|0|0|0|0|0|0|0|0|0|0|0|0|0|0|0|0|0|0|0|0|0|0|0|0|0|0|0|0|0|0|0|0|0|0|0|0|0|0|0|0|0|0|0|0|0|0|0|0|0|0|0|0|0|0|0|0|0|0|0|0|0|0|0|0|0|0|0|0|0|0|0|0|0|0|0|0|0|0|0|0|0|0|0|0|0|0|0|0|0|0|0|0|0|0|0|0|0|0|0|0|0|0|0|0|0|0|0|0|0|0|0|0|0|0|0|0|0|0|0|0|0|0|0|0|0|0|0|0|0|0|0|0|0|0|0|0|0|0|0|0|</MDI>
      <MDI key="STATISTICS_HISTOMAX">255</MDI>
      <MDI key="STATISTICS_HISTOMIN">0</MDI>
      <MDI key="STATISTICS_HISTONUMBINS">256</MDI>
      <MDI key="STATISTICS_MAXIMUM">25</MDI>
      <MDI key="STATISTICS_MEAN">10.698647624454</MDI>
      <MDI key="STATISTICS_MEDIAN">0</MDI>
      <MDI key="STATISTICS_MINIMUM">2</MDI>
      <MDI key="STATISTICS_MODE">0</MDI>
      <MDI key="STATISTICS_SKIPFACTORX">1</MDI>
      <MDI key="STATISTICS_SKIPFACTORY">1</MDI>
      <MDI key="STATISTICS_STDDEV">3.4908638736311</MDI>
      <MDI key="STATISTICS_VALID_PERCENT">39.77</MDI>
    </Metadata>
  </PAMRasterBand>
</PAMDataset>
