<PAMDataset>
  <PAMRasterBand band="1">
    <Description>Layer_1</Description>
    <Metadata domain="IMAGE_STRUCTURE">
      <MDI key="COMPRESSION">RLE</MDI>
    </Metadata>
    <Metadata>
      <MDI key="LAYER_TYPE">thematic</MDI>
      <MDI key="STATISTICS_EXCLUDEDVALUES"></MDI>
      <MDI key="STATISTICS_HISTOBINVALUES">0|0|737302|1233577|5179472|1462077|13822255|12833691|5155793|3753278|24086202|6872313|18987670|27318152|3680249|6796130|406|35599|8557548|641461|573210|28822172|274141|268568|0|0|0|0|0|0|0|0|0|0|0|0|0|0|0|0|0|0|0|0|0|0|0|0|0|0|0|0|0|0|0|0|0|0|0|0|0|0|0|0|0|0|0|0|0|0|0|0|0|0|0|0|0|0|0|0|0|0|0|0|0|0|0|0|0|0|0|0|0|0|0|0|0|0|0|0|0|0|0|0|0|0|0|0|0|0|0|0|0|0|0|0|0|0|0|0|0|0|0|0|0|0|0|0|0|0|0|0|0|0|0|0|0|0|0|0|0|0|0|0|0|0|0|0|0|0|0|0|0|0|0|0|0|0|0|0|0|0|0|0|0|0|0|0|0|0|0|0|0|0|0|0|0|0|0|0|0|0|0|0|0|0|0|0|0|0|0|0|0|0|0|0|0|0|0|0|0|0|0|0|0|0|0|0|0|0|0|0|0|0|0|0|0|0|0|0|0|0|0|0|0|0|0|0|0|0|0|0|0|0|0|0|0|0|0|0|0|0|0|0|0|0|0|0|0|0|0|0|0|0|0|0|</MDI>
      <MDI key="STATISTICS_HISTOMAX">255</MDI>
      <MDI key="STATISTICS_HISTOMIN">0</MDI>
      <MDI key="STATISTICS_HISTONUMBINS">256</MDI>
      <MDI key="STATISTICS_MAXIMUM">23</MDI>
      <MDI key="STATISTICS_MEAN">12.447643095937</MDI>
      <MDI key="STATISTICS_MEDIAN">0</MDI>
      <MDI key="STATISTICS_MINIMUM">2</MDI>
      <MDI key="STATISTICS_MODE">0</MDI>
      <MDI key="STATISTICS_SKIPFACTORX">1</MDI>
      <MDI key="STATISTICS_SKIPFACTORY">1</MDI>
      <MDI key="STATISTICS_STDDEV">5.1029440013824</MDI>
      <MDI key="STATISTICS_VALID_PERCENT">42.77</MDI>
    </Metadata>
  </PAMRasterBand>
</PAMDataset>
